btrfs_backup_ng/__init__.py
btrfs_backup_ng/__logger__.py
btrfs_backup_ng/__main__.py
btrfs_backup_ng/__util__.py
btrfs_backup_ng/__util__.pyi
btrfs_backup_ng/_legacy_main.py
btrfs_backup_ng/btrbk_import.py
btrfs_backup_ng/notifications.py
btrfs_backup_ng/retention.py
btrfs_backup_ng/ssh_transfer.py
btrfs_backup_ng/systemd_utils.py
btrfs_backup_ng/transaction.py
btrfs_backup_ng/cli/__init__.py
btrfs_backup_ng/cli/common.py
btrfs_backup_ng/cli/completions.py
btrfs_backup_ng/cli/config_cmd.py
btrfs_backup_ng/cli/dispatcher.py
btrfs_backup_ng/cli/doctor.py
btrfs_backup_ng/cli/estimate.py
btrfs_backup_ng/cli/install.py
btrfs_backup_ng/cli/list_cmd.py
btrfs_backup_ng/cli/manpages.py
btrfs_backup_ng/cli/prune.py
btrfs_backup_ng/cli/restore.py
btrfs_backup_ng/cli/run.py
btrfs_backup_ng/cli/snapper_cmd.py
btrfs_backup_ng/cli/snapshot.py
btrfs_backup_ng/cli/status.py
btrfs_backup_ng/cli/transfer.py
btrfs_backup_ng/cli/transfers_cmd.py
btrfs_backup_ng/cli/verify.py
btrfs_backup_ng/cli/wizard_utils.py
btrfs_backup_ng/config/__init__.py
btrfs_backup_ng/config/loader.py
btrfs_backup_ng/config/schema.py
btrfs_backup_ng/core/__init__.py
btrfs_backup_ng/core/chunked_transfer.py
btrfs_backup_ng/core/doctor.py
btrfs_backup_ng/core/errors.py
btrfs_backup_ng/core/estimate.py
btrfs_backup_ng/core/execution.py
btrfs_backup_ng/core/operations.py
btrfs_backup_ng/core/planning.py
btrfs_backup_ng/core/progress.py
btrfs_backup_ng/core/restore.py
btrfs_backup_ng/core/retry.py
btrfs_backup_ng/core/space.py
btrfs_backup_ng/core/state.py
btrfs_backup_ng/core/transfer.py
btrfs_backup_ng/core/verify.py
btrfs_backup_ng/detection/__init__.py
btrfs_backup_ng/detection/classifier.py
btrfs_backup_ng/detection/models.py
btrfs_backup_ng/detection/scanner.py
btrfs_backup_ng/endpoint/__init__.py
btrfs_backup_ng/endpoint/common.py
btrfs_backup_ng/endpoint/common.pyi
btrfs_backup_ng/endpoint/local.py
btrfs_backup_ng/endpoint/raw.py
btrfs_backup_ng/endpoint/raw_metadata.py
btrfs_backup_ng/endpoint/shell.py
btrfs_backup_ng-0.8.2.dist-info/licenses/LICENSE
btrfs_backup_ng-0.8.2.dist-info/METADATA
btrfs_backup_ng-0.8.2.dist-info/WHEEL
btrfs_backup_ng-0.8.2.dist-info/entry_points.txt
btrfs_backup_ng-0.8.2.dist-info/top_level.txt
btrfs_backup_ng-0.8.2.dist-info/RECORD
