Metadata-Version: 2.4
Name: btrfs-backup-ng
Version: 0.8.2
Summary: Complete btrfs backup solution with automated snapshots, incremental transfers, restore functionality, snapper integration, and systemd scheduling
Author-email: Michael Berry <trismegustis@gmail.com>
License: The MIT License (MIT)
Project-URL: Homepage, https://github.com/berrym/btrfs-backup-ng
Classifier: Programming Language :: Python :: 3
Classifier: Operating System :: POSIX :: Linux
Requires-Python: >=3.11
License-File: LICENSE
Requires-Dist: filelock
Requires-Dist: rich
Requires-Dist: paramiko
Provides-Extra: test
Requires-Dist: pytest>=7.0; extra == "test"
Requires-Dist: pytest-cov>=4.0; extra == "test"
Requires-Dist: pytest-asyncio>=0.23.0; extra == "test"
Provides-Extra: dev
Requires-Dist: pytest>=7.0; extra == "dev"
Requires-Dist: pytest-cov>=4.0; extra == "dev"
Requires-Dist: pytest-asyncio>=0.23.0; extra == "dev"
Requires-Dist: ruff>=0.1.0; extra == "dev"
Requires-Dist: mypy>=1.0; extra == "dev"
Requires-Dist: types-paramiko>=3.0; extra == "dev"
Dynamic: license-file
